varion/__init__.py
varion/core.py
varion-0.1.0.dist-info/licenses/LICENSE
varion-0.1.0.dist-info/METADATA
varion-0.1.0.dist-info/WHEEL
varion-0.1.0.dist-info/top_level.txt
varion-0.1.0.dist-info/RECORD
